aws_xray_lambda_segment_shim/__init__.py
aws_xray_lambda_segment_shim/exceptions.py
aws_xray_lambda_segment_shim/py.typed
aws_xray_lambda_segment_shim/recorder.py
aws_xray_lambda_segment_shim/segment.py
aws_xray_lambda_segment_shim-0.5.3.dist-info/LICENSE
aws_xray_lambda_segment_shim-0.5.3.dist-info/METADATA
aws_xray_lambda_segment_shim-0.5.3.dist-info/WHEEL
aws_xray_lambda_segment_shim-0.5.3.dist-info/top_level.txt
aws_xray_lambda_segment_shim-0.5.3.dist-info/RECORD
