Metadata-Version: 2.1
Name: aws-xray-lambda-segment-shim
Version: 0.5.3
Summary: A shim which faciliates the AWS X-Ray tracing of Lambda Functions invoked by triggers which don't have native X-Ray support.
Home-page: https://github.com/sam-martin/aws-xray-lambda-segment-shim
Author: Sam Martin
Author-email: samjackmartin+aws-xray-lambda-segment-shim@gmail.com
License: UNKNOWN
Platform: UNKNOWN
Requires-Python: >=3.6.0
License-File: LICENSE
Requires-Dist: aws-xray-sdk
Requires-Dist: jmespath
